mr_millionaire/__init__.py
mr_millionaire/main.py
mr_millionaire/libs/__init__.py
mr_millionaire/libs/choice_base.py
mr_millionaire/libs/config_handler.py
mr_millionaire/libs/lib_constant.py
mr_millionaire/libs/llm_handler.py
mr_millionaire/libs/memory_handler.py
mr_millionaire/libs/schema.py
mr_millionaire/libs/utility.py
mr_millionaire/libs/choices/__init__.py
mr_millionaire/libs/choices/config_manager.py
mr_millionaire/libs/choices/game_runner.py
mr_millionaire/libs/choices/history_manager.py
mr_millionaire/libs/choices/mem_manager.py
mr_millionaire-0.1.1.dist-info/licenses/LICENSE
mr_millionaire-0.1.1.dist-info/METADATA
mr_millionaire-0.1.1.dist-info/WHEEL
mr_millionaire-0.1.1.dist-info/entry_points.txt
mr_millionaire-0.1.1.dist-info/top_level.txt
mr_millionaire-0.1.1.dist-info/RECORD
