Metadata-Version: 2.4
Name: mr-millionaire
Version: 0.1.1
Summary: A console-based AI quiz game inspired by Who Wants to Be a Millionaire.
Author-email: Mohamed Jubair <jakirjubair.555@gmail.com>
Requires-Python: >=3.12
License-File: LICENSE
Requires-Dist: python-dotenv>=0.9.9
Requires-Dist: litellm>=1.73.6
Requires-Dist: numpy>=2.3.1
Requires-Dist: tabulate>=0.9.0
Provides-Extra: dev
Requires-Dist: pytest>=8.4.1; extra == "dev"
Requires-Dist: ruff>=0.12.1; extra == "dev"
Dynamic: license-file
